rtl/sequential/IMEM.sv
`timescale 1ns/1ps

// module: IMEM 64kb
// author: Ryan Cramer

module IMEM #(parameter ADDR_DEPTH = 14)
(
    input CLK,
    input RDEN,
    input [ADDR_DEPTH-1:0] ADDR,
    output logic [31:0] MEM_OUT
);

(* rom_style = "{distributed | block}" *)
(* rom_decomp = "power" *) logic [31:0] rom_64kb[0:2**ADDR_DEPTH-1];

initial begin
    $readmemh("eel_program.mem", rom_64kb, 0, 2**ADDR_DEPTH-1);
end

always_ff@(posedge CLK) begin
    if(RDEN) begin
        MEM_OUT <= rom_64kb[ADDR];
    end
    else begin
        MEM_OUT <= 'b0;
    end
end

endmodule

tests/tb_IMEM/tb_IMEM.sv
`timescale 1ns/1ps

module tb_IMEM ();

    logic CLK;
    logic RDEN;
    logic [31:0] PC_OUT;
    logic [13:0] ADDR;
    
    assign ADDR = PC_OUT[15:2];

    IMEM UUT(
        .CLK(CLK),
        .RDEN(RDEN),
        .ADDR(ADDR),
        .MEM_OUT()
    );

    initial begin
        $dumpfile("tb_IMEM.vcd");
        $dumpvars(0, tb_IMEM);
    end

    initial begin
        #5 CLK = 1'b0;
        forever #5 CLK = ~CLK;
    end

    always begin
        
        $monitorh("instruction: ", UUT.MEM_OUT);
        
        #10 RDEN <= 1'b0;
            PC_OUT <= 32'd0;
        
        #10 RDEN <= 1'b1;
            PC_OUT <= 32'd0;
        
        #10 RDEN <= 1'b1;
            PC_OUT <= 32'd4;
        
        #10 RDEN <= 1'b1;
            PC_OUT <= 32'd8;
        
        #10 RDEN <= 1'b1;
            PC_OUT <= 32'd12;
        
        #10 RDEN <= 1'b1;
            PC_OUT <= 32'd16;
        
        #10 RDEN <= 1'b1;
            PC_OUT <= 32'd20;

        #10 RDEN <= 1'b1;
            PC_OUT <= 32'd24;
        

        #20 $finish;
    end
endmodule

tests/tb_IMEM/tb_IMEM.vcd
$version Generated by VerilatedVcd $end
$timescale 1ps $end
 $scope module $rootio $end
 $upscope $end
 $scope module tb_IMEM $end
  $var wire 1 & CLK $end
  $var wire 1 # RDEN $end
  $var wire 32 $ PC_OUT [31:0] $end
  $var wire 14 % ADDR [13:0] $end
  $scope module UUT $end
   $var wire 32 ( ADDR_DEPTH [31:0] $end
   $var wire 1 & CLK $end
   $var wire 1 # RDEN $end
   $var wire 14 % ADDR [13:0] $end
   $var wire 32 ' MEM_OUT [31:0] $end
  $upscope $end
 $upscope $end
$enddefinitions $end


#0
0#
b00000000000000000000000000000000 $
b00000000000000 %
0&
b00000000000000000000000000000000 '
b00000000000000000000000000001110 (
#5000
#10000
1&
#15000
0&
#20000
1#
1&
#25000
0&
#30000
b00000000000000000000000000000100 $
b00000000000001 %
1&
b00000000000100000000000010010111 '
#35000
0&
#40000
b00000000000000000000000000001000 $
b00000000000010 %
1&
b00000000000000000000000000010011 '
#45000
0&
#50000
b00000000000000000000000000001100 $
b00000000000011 %
1&
#55000
0&
#60000
b00000000000000000000000000010000 $
b00000000000100 %
1&
b00000000111110100000010010110111 '
#65000
0&
#70000
b00000000000000000000000000010100 $
b00000000000101 %
1&
b00000000000000000000000000010011 '
#75000
0&
#80000
b00000000000000000000000000011000 $
b00000000000110 %
1&
#85000
0&
#90000
1&
b00000110010000001000000010010011 '
