rtl/combinational/ALU.sv
`timescale 1ns/1ps

// module: ALU
// author: Ryan Cramer
//
// supported operations:
// 4'b0000 = ADD
// 4'b1000 = SUB
// 4'b0110 = OR
// 4'b0111 = AND
// 4'b0100 = XOR
// 4'b0101 = SRL
// 4'b0001 = SLL
// 4'b1101 = SRA
// 4'b0010 = SLT
// 4'b0011 = SLTU
// 4'b1001 = LUI-Copy


module ALU #(parameter n = 32)
(
	input [n-1:0] OP_A,
	input [n-1:0] OP_B,
	input [3:0] ALU_FUN,
	output logic ZERO,
	output logic [n-1:0] RESULT	
);


	always_comb begin
		case(ALU_FUN)
			4'b0000: RESULT = OP_A + OP_B;
			4'b1000: RESULT = OP_A - OP_B;
			4'b0110: RESULT = OP_A | OP_B;
			4'b0111: RESULT = OP_A & OP_B;
			4'b0100: RESULT = OP_A >> OP_B;
			4'b0001: RESULT = OP_A << OP_B;
			4'b1101: RESULT = OP_A >>> OP_B;
			4'b0010: RESULT = {31'b0, ($signed(OP_A) < $signed(OP_B))};
			4'b0011: RESULT = {31'b0, ($unsigned(OP_A) < $unsigned(OP_B))};
			4'b1001: RESULT = OP_A;
			default: RESULT = 'b0;
		endcase
	end
	
	assign ZERO = (RESULT == 0);

endmodule

tests/tb_ALU/tb_ALU.sv
`timescale 1ns/1ps

// test: tb_ALU
// author: Ryan Cramer

module tb_ALU();

logic [31:0] OP_A;
logic [31:0] OP_B;
logic [3:0] ALU_FUN;

/* |------- ALU_FUN Table -------|
   |   FUN_NAME   |    ALU_FUN   |
   |_____________________________|
   |      ADD     |     4'b0000  |
   |      SUB     |     4'b1000  |
   |      OR      |     4'b0110  |
   |      AND     |     4'b0111  |
   |      XOR     |     4'b0100  |
   |      SRL     |     4'b0101  |
   |      SLL     |     4'b0001  |
   |      SRA     |     4'b1101  |
   |      SLT     |     4'b0010  |
   |      SLTU    |     4'b0011  |
   |      LUI     |     4'b1001  |
   |_____________________________| */
   


    ALU UUT(
        .OP_A(OP_A),
        .OP_B(OP_B),
        .ALU_FUN(ALU_FUN),
        .RESULT(),
        .ZERO()
    );

    initial begin
        $dumpfile("tb_ALU.vcd");
        $dumpvars(0, tb_ALU);
    end

    initial begin
        OP_A = 'b0;
        OP_B = 'b0;
    end

    

    always begin
        $monitorh("OP_A =", OP_A, "\tOP_B =", OP_B,
         "\tALU_FUN = ", ALU_FUN, "\n RESULT = ", UUT.RESULT, "\t ZERO = ", UUT.ZERO);
        #10 OP_A = 32'h0000_0000;
            OP_B = 32'h0000_0000;
            ALU_FUN = 4'b0000; // ADD
        

        #10 OP_A = 32'h1000_0000;
            OP_B = 32'h1000_0000;
            ALU_FUN = 4'b0000; // ADD
        

        #10 OP_A = 32'h1000_0000;
            OP_B = 32'h1000_0000;
            ALU_FUN = 4'b1000; // SUB
        
        #10 OP_A = 32'h1000_FFFF;
            OP_B = 32'h1000_0000;
            ALU_FUN = 4'b0110; // OR
        
        #10 OP_A = 32'h1000_FFFF;
            OP_B = 32'h1000_0000;
            ALU_FUN = 4'b0111; // AND

        #10 OP_A = 32'hF0F0_F0F0;
            OP_B = 32'hFFFF_FFFF;
            ALU_FUN = 4'b0100; // XOR

        #10 OP_A = 32'h0000_0004;
            OP_B = 32'h0000_0002;
            ALU_FUN = 4'b0101; // SRL

        #10 OP_A = 32'h0000_0004;
            OP_B = 32'h0000_0002;
            ALU_FUN = 4'b0001; // SLL
        
        #10 OP_A = 32'h0000_000f;
            OP_B = 32'h0000_0001;
            ALU_FUN = 4'b1101; // SRA
        
        #10 OP_A = 32'h8000_0001;
            OP_B = 32'h8000_0010;
            ALU_FUN = 4'b0010; // SLT
        
        #10 OP_A = 32'h0000_0011;
            OP_B = 32'h0000_0010;
            ALU_FUN = 4'b0010; // SLT
        
        #10 OP_A = 32'h0000_0001;
            OP_B = 32'h0000_0010;
            ALU_FUN = 4'b0011; // SLTU

        #10 OP_A = 32'h0000_0011;
            OP_B = 32'h0000_0010;
            ALU_FUN = 4'b0011; // SLTU
        
        #10 OP_A = 32'hFFFF_0000;
            OP_B = 32'h0000_FFFF;
            ALU_FUN = 4'b1001; // LUI
            
        #10 $finish;
    end

endmodule

tests/tb_ALU/tb_ALU.vcd
$version Generated by VerilatedVcd $end
$timescale 1ps $end
 $scope module $rootio $end
 $upscope $end
 $scope module tb_ALU $end
  $var wire 32 # OP_A [31:0] $end
  $var wire 32 $ OP_B [31:0] $end
  $var wire 4 % ALU_FUN [3:0] $end
  $scope module UUT $end
   $var wire 32 ( n [31:0] $end
   $var wire 32 # OP_A [31:0] $end
   $var wire 32 $ OP_B [31:0] $end
   $var wire 4 % ALU_FUN [3:0] $end
   $var wire 1 & ZERO $end
   $var wire 32 ' RESULT [31:0] $end
  $upscope $end
 $upscope $end
$enddefinitions $end


#0
b00000000000000000000000000000000 #
b00000000000000000000000000000000 $
b0000 %
1&
b00000000000000000000000000000000 '
b00000000000000000000000000100000 (
#10000
#20000
b00010000000000000000000000000000 #
b00010000000000000000000000000000 $
0&
b00100000000000000000000000000000 '
#30000
b1000 %
1&
b00000000000000000000000000000000 '
#40000
b00010000000000001111111111111111 #
b0110 %
0&
b00010000000000001111111111111111 '
#50000
b0111 %
b00010000000000000000000000000000 '
#60000
b11110000111100001111000011110000 #
b11111111111111111111111111111111 $
b0100 %
1&
b00000000000000000000000000000000 '
#70000
b00000000000000000000000000000100 #
b00000000000000000000000000000010 $
b0101 %
0&
b00000000000000000000000000000001 '
#80000
b0001 %
b00000000000000000000000000010000 '
#90000
b00000000000000000000000000001111 #
b00000000000000000000000000000001 $
b1101 %
b00000000000000000000000000000111 '
#100000
b10000000000000000000000000000001 #
b10000000000000000000000000010000 $
b0010 %
b00000000000000000000000000000001 '
#110000
b00000000000000000000000000010001 #
b00000000000000000000000000010000 $
1&
b00000000000000000000000000000000 '
#120000
b00000000000000000000000000000001 #
b0011 %
0&
b00000000000000000000000000000001 '
#130000
b00000000000000000000000000010001 #
1&
b00000000000000000000000000000000 '
#140000
b11111111111111110000000000000000 #
b00000000000000001111111111111111 $
b1001 %
0&
b11111111111111110000000000000000 '
