rtl/mux/MUX8T1.sv
`timescale 1ns/1ps

// module: MUX 8 to 1
// author: Ryan Cramer

module MUX8T1 #(parameter n = 32)
(
	input [2:0] SEL,
	input [n-1:0] D0,
	input [n-1:0] D1,
	input [n-1:0] D2,
	input [n-1:0] D3,
	input [n-1:0] D4,
	input [n-1:0] D5,
	input [n-1:0] D6,
	input [n-1:0] D7,	
	output logic [n-1:0] DOUT
);

	always_comb begin
		case(SEL)
			3'b000: DOUT = D0;
			3'b001: DOUT = D1;
			3'b010: DOUT = D2;
			3'b011: DOUT = D3;
			3'b100: DOUT = D4;
			3'b101: DOUT = D5;
			3'b110: DOUT = D6;
			3'b111: DOUT = D7;
			default: DOUT = D0;
		endcase
	end

endmodule

tests/tb_MUX8T1/tb_MUX8T1.sv
`timescale 1ns/1ps

module tb_MUX8T1 ();

    logic [31:0] D0;
    logic [31:0] D1;
    logic [31:0] D2;
    logic [31:0] D3;
    logic [31:0] D4;
    logic [31:0] D5;
    logic [31:0] D6;
    logic [31:0] D7;
    logic [2:0] SEL;
    
    MUX8T1 UUT(
        .D0(D0),
        .D1(D1),
        .D2(D2),
        .D3(D3),
        .D4(D4),
        .D5(D5),
        .D6(D6),
        .D7(D7),
        .SEL(SEL),
        .DOUT()
    );

    initial begin
        $dumpfile("tb_MUX8T1.vcd");
        $dumpvars(0,tb_MUX8T1);
    end

    initial begin
        D0 = 32'b0;
        D1 = 32'b0;
        D2 = 32'b0;
        D3 = 32'b0;
        D4 = 32'b0;
        D5 = 32'b0;
        D6 = 32'b0;
        D7 = 32'b0;
        SEL = 3'b0;
    end

    always begin

        #10 SEL <= 3'b000;     // SEL D0
            D0 <= 32'habababab;
            D1 <= 32'haaaabbbb;
            D2 <= 32'hacacacac;
            D3 <= 32'haaaacccc;
            D4 <= 32'hbcbcbcbc;
            D5 <= 32'hbbbbcccc;
            D6 <= 32'hdcdcdcdc;
            D7 <= 32'hddddcccc;
        
        #10 SEL <= 3'b001;     // SEL D1
            D0 <= 32'habababab;
            D1 <= 32'haaaabbbb;
            D2 <= 32'hacacacac;
            D3 <= 32'haaaacccc;
            D4 <= 32'hbcbcbcbc;
            D5 <= 32'hbbbbcccc;
            D6 <= 32'hdcdcdcdc;
            D7 <= 32'hddddcccc;
        
        #10 SEL <= 3'b010;     // SEL D2
            D0 <= 32'habababab;
            D1 <= 32'haaaabbbb;
            D2 <= 32'hacacacac;
            D3 <= 32'haaaacccc;
            D4 <= 32'hbcbcbcbc;
            D5 <= 32'hbbbbcccc;
            D6 <= 32'hdcdcdcdc;
            D7 <= 32'hddddcccc;
        
        #10 SEL <= 3'b011;     // SEL D3
            D0 <= 32'habababab;
            D1 <= 32'haaaabbbb;
            D2 <= 32'hacacacac;
            D3 <= 32'haaaacccc;
            D4 <= 32'hbcbcbcbc;
            D5 <= 32'hbbbbcccc;
            D6 <= 32'hdcdcdcdc;
            D7 <= 32'hddddcccc;
        
        #10 SEL <= 3'b100;     // SEL D4
            D0 <= 32'habababab;
            D1 <= 32'haaaabbbb;
            D2 <= 32'hacacacac;
            D3 <= 32'haaaacccc;
            D4 <= 32'hbcbcbcbc;
            D5 <= 32'hbbbbcccc;
            D6 <= 32'hdcdcdcdc;
            D7 <= 32'hddddcccc;

        #10 SEL <= 3'b101;     // SEL D5
            D0 <= 32'habababab;
            D1 <= 32'haaaabbbb;
            D2 <= 32'hacacacac;
            D3 <= 32'haaaacccc;
            D4 <= 32'hbcbcbcbc;
            D5 <= 32'hbbbbcccc;
            D6 <= 32'hdcdcdcdc;
            D7 <= 32'hddddcccc;

        #10 SEL <= 3'b110;     // SEL D6
            D0 <= 32'habababab;
            D1 <= 32'haaaabbbb;
            D2 <= 32'hacacacac;
            D3 <= 32'haaaacccc;
            D4 <= 32'hbcbcbcbc;
            D5 <= 32'hbbbbcccc;
            D6 <= 32'hdcdcdcdc;
            D7 <= 32'hddddcccc;

        #10 SEL <= 3'b111;     // SEL D7
            D0 <= 32'habababab;
            D1 <= 32'haaaabbbb;
            D2 <= 32'hacacacac;
            D3 <= 32'haaaacccc;
            D4 <= 32'hbcbcbcbc;
            D5 <= 32'hbbbbcccc;
            D6 <= 32'hdcdcdcdc;
            D7 <= 32'hddddcccc;
        
        
    
        #10 $finish;

    end
endmodule

tests/tb_MUX8T1/tb_MUX8T1.vcd
$version Generated by VerilatedVcd $end
$timescale 1ps $end
 $scope module $rootio $end
 $upscope $end
 $scope module tb_MUX8T1 $end
  $var wire 32 # D0 [31:0] $end
  $var wire 32 $ D1 [31:0] $end
  $var wire 32 % D2 [31:0] $end
  $var wire 32 & D3 [31:0] $end
  $var wire 32 ' D4 [31:0] $end
  $var wire 32 ( D5 [31:0] $end
  $var wire 32 ) D6 [31:0] $end
  $var wire 32 * D7 [31:0] $end
  $var wire 3 + SEL [2:0] $end
  $scope module UUT $end
   $var wire 32 - n [31:0] $end
   $var wire 3 + SEL [2:0] $end
   $var wire 32 # D0 [31:0] $end
   $var wire 32 $ D1 [31:0] $end
   $var wire 32 % D2 [31:0] $end
   $var wire 32 & D3 [31:0] $end
   $var wire 32 ' D4 [31:0] $end
   $var wire 32 ( D5 [31:0] $end
   $var wire 32 ) D6 [31:0] $end
   $var wire 32 * D7 [31:0] $end
   $var wire 32 , DOUT [31:0] $end
  $upscope $end
 $upscope $end
$enddefinitions $end


#0
b00000000000000000000000000000000 #
b00000000000000000000000000000000 $
b00000000000000000000000000000000 %
b00000000000000000000000000000000 &
b00000000000000000000000000000000 '
b00000000000000000000000000000000 (
b00000000000000000000000000000000 )
b00000000000000000000000000000000 *
b000 +
b00000000000000000000000000000000 ,
b00000000000000000000000000100000 -
#10000
b10101011101010111010101110101011 #
b10101010101010101011101110111011 $
b10101100101011001010110010101100 %
b10101010101010101100110011001100 &
b10111100101111001011110010111100 '
b10111011101110111100110011001100 (
b11011100110111001101110011011100 )
b11011101110111011100110011001100 *
b10101011101010111010101110101011 ,
#20000
b001 +
b10101010101010101011101110111011 ,
#30000
b010 +
b10101100101011001010110010101100 ,
#40000
b011 +
b10101010101010101100110011001100 ,
#50000
b100 +
b10111100101111001011110010111100 ,
#60000
b101 +
b10111011101110111100110011001100 ,
#70000
b110 +
b11011100110111001101110011011100 ,
#80000
b111 +
b11011101110111011100110011001100 ,
