rtl/memory/DMEM.sv
`timescale 1ns/1ps

// module: Data Memory 64kB
// author: Ryan Cramer

module DMEM #(parameter ADDR_DEPTH = 14) 
(
    input CLK,
    input RDEN,
    input WEN,
    input [1:0] BYTE_SEL,
    input SIGN,
    input [ADDR_DEPTH-1:0] ADDR,
    input [31:0] DATA_IN,
    output logic [31:0] DATA_OUT
);
    (* ram_style = "block" *) logic [31:0] ram_64kb [0:2**ADDR_DEPTH-1];

    logic [31:0] data_out;
    logic [31:0] data_in;
    
    always_comb begin // DATA_OUT BYTE CONVERSION
        case(BYTE_SEL)
            2'b00: begin // BYTE
                data_out = SIGN ? {{24{1'b1}}, ram_64kb[ADDR][7:0]} : {{24{1'b0}}, ram_64kb[ADDR][7:0]};
            end
            2'b01: begin // HALF
                data_out = SIGN ? {{16{1'b1}}, ram_64kb[ADDR][15:0]} : {{16{1'b0}}, ram_64kb[ADDR][15:0]};
            end
            2'b10: begin // WORD
                data_out = ram_64kb[ADDR];
            end
            default: begin // default = WORD
                data_out = ram_64kb[ADDR];
            end
        endcase
    end

    always_comb begin // DATA_IN BYTE CONVERSION
        case(BYTE_SEL)
            2'b00: begin // BYTE
                data_in = SIGN ? {{24{1'b1}}, DATA_IN[7:0]} : {{24{1'b0}}, DATA_IN[7:0]};
            end
            2'b01: begin // HALF
                data_in = SIGN ? {{16{1'b1}}, DATA_IN[15:0]} : {{16{1'b0}}, DATA_IN[15:0]};
            end
            2'b10: begin // WORD
                data_in = DATA_IN;
            end
            default: begin // default = WORD
                data_in = DATA_IN;
            end
        endcase
    end

    always@(posedge CLK) begin
        if(RDEN) begin
            DATA_OUT <= data_out;
        end
        else if (WEN) begin
            ram_64kb[ADDR] <= data_in; 
            DATA_OUT <= 'b0;  
        end
        else 
            DATA_OUT <= 'b0;  
    end

endmodule

tests/tb_DMEM/tb_DMEM.sv
`timescale 1ns/1ps

module tb_DMEM();

    logic RDEN, WEN, SIGN;
    logic [1:0] BYTE_SEL;
    logic [13:0] ADDR;
    logic [31:0] DATA_IN;
    logic CLK;

    DMEM UUT(
        .CLK(CLK),
        .RDEN(RDEN),
        .WEN(WEN),
        .BYTE_SEL(BYTE_SEL),
        .SIGN(SIGN),
        .ADDR(ADDR),
        .DATA_IN(DATA_IN),
        .DATA_OUT()
    );

    initial begin
        $dumpfile("tb_DMEM.vcd");
        $dumpvars(0, tb_DMEM);
    end

    initial begin
        #5 CLK = 1'b0;
        forever #5 CLK = ~CLK;
    end

    always begin

        // NOP
        #10 RDEN <= 1'b0;
            WEN <= 1'b0;
            BYTE_SEL <= 2'b00;
            SIGN <= 1'b0;
            ADDR <= 14'b0;
            DATA_IN <= 32'hdeadbeef;
        
        // WRITE
        #10 RDEN <= 1'b0;
            WEN <= 1'b1;
            BYTE_SEL <= 2'b10;
            SIGN <= 1'b0;
            ADDR <= 14'b0;
            DATA_IN <= 32'hdeadbeef;
        
        // READ
        #10 RDEN <= 1'b1;
            WEN <= 1'b0;
            BYTE_SEL <= 2'b10;
            SIGN <= 1'b0;
            ADDR <= 14'b0;
            DATA_IN <= 32'h0000_0000;

        // WRITE
        #10 RDEN <= 1'b0;
            WEN <= 1'b1;
            BYTE_SEL <= 2'b00;
            SIGN <= 1'b0;
            ADDR <= 14'd4;
            DATA_IN <= 32'hdeadbeef;
        
        // WRITE
        #10 RDEN <= 1'b0;
            WEN <= 1'b1;
            BYTE_SEL <= 2'b01;
            SIGN <= 1'b0;
            ADDR <= 14'd8;
            DATA_IN <= 32'hdeadbeef;
        
        // WRITE
        #10 RDEN <= 1'b0;
            WEN <= 1'b1;
            BYTE_SEL <= 2'b00;
            SIGN <= 1'b1;
            ADDR <= 14'd12;
            DATA_IN <= 32'hdeadbeef;
        
        // READ
        #10 RDEN <= 1'b1;
            WEN <= 1'b0;
            BYTE_SEL <= 2'b10;
            SIGN <= 1'b0;
            ADDR <= 14'd4;
            DATA_IN <= 32'h0000_0000;
        
        // READ
        #10 RDEN <= 1'b1;
            WEN <= 1'b0;
            BYTE_SEL <= 2'b10;
            SIGN <= 1'b0;
            ADDR <= 14'd8;
            DATA_IN <= 32'h0000_0000;
        
        // READ
        #10 RDEN <= 1'b1;
            WEN <= 1'b0;
            BYTE_SEL <= 2'b10;
            SIGN <= 1'b0;
            ADDR <= 14'd12;
            DATA_IN <= 32'h0000_0000;

        // READ
        #10 RDEN <= 1'b1;
            WEN <= 1'b0;
            BYTE_SEL <= 2'b01;
            SIGN <= 1'b1;
            ADDR <= 14'd8;
            DATA_IN <= 32'h0000_0000;



        #20 $finish;
    end
endmodule

tests/tb_DMEM/tb_DMEM.vcd
$version Generated by VerilatedVcd $end
$timescale 1ps $end
 $scope module $rootio $end
 $upscope $end
 $scope module tb_DMEM $end
  $var wire 1 # RDEN $end
  $var wire 1 $ WEN $end
  $var wire 1 % SIGN $end
  $var wire 2 & BYTE_SEL [1:0] $end
  $var wire 14 ' ADDR [13:0] $end
  $var wire 32 ( DATA_IN [31:0] $end
  $var wire 1 * CLK $end
  $scope module UUT $end
   $var wire 32 - ADDR_DEPTH [31:0] $end
   $var wire 1 * CLK $end
   $var wire 1 # RDEN $end
   $var wire 1 $ WEN $end
   $var wire 2 & BYTE_SEL [1:0] $end
   $var wire 1 % SIGN $end
   $var wire 14 ' ADDR [13:0] $end
   $var wire 32 ( DATA_IN [31:0] $end
   $var wire 32 + DATA_OUT [31:0] $end
   $var wire 32 , data_out [31:0] $end
   $var wire 32 ) data_in [31:0] $end
  $upscope $end
 $upscope $end
$enddefinitions $end


#0
0#
0$
0%
b00 &
b00000000000000 '
b00000000000000000000000000000000 (
b00000000000000000000000000000000 )
0*
b00000000000000000000000000000000 +
b00000000000000000000000000000000 ,
b00000000000000000000000000001110 -
#5000
#10000
b11011110101011011011111011101111 (
b00000000000000000000000011101111 )
1*
#15000
0*
#20000
1$
b10 &
b11011110101011011011111011101111 )
1*
#25000
0*
#30000
1#
0$
b00000000000000000000000000000000 (
b00000000000000000000000000000000 )
1*
b11011110101011011011111011101111 ,
#35000
0*
#40000
0#
1$
b00 &
b00000000000100 '
b11011110101011011011111011101111 (
b00000000000000000000000011101111 )
1*
b11011110101011011011111011101111 +
b00000000000000000000000000000000 ,
#45000
0*
#50000
b01 &
b00000000001000 '
b00000000000000001011111011101111 )
1*
b00000000000000000000000000000000 +
#55000
0*
#60000
1%
b00 &
b00000000001100 '
b11111111111111111111111111101111 )
1*
b11111111111111111111111100000000 ,
#65000
0*
#70000
1#
0$
0%
b10 &
b00000000000100 '
b00000000000000000000000000000000 (
b00000000000000000000000000000000 )
1*
b00000000000000000000000011101111 ,
#75000
0*
#80000
b00000000001000 '
1*
b00000000000000000000000011101111 +
b00000000000000001011111011101111 ,
#85000
0*
#90000
b00000000001100 '
1*
b00000000000000001011111011101111 +
b11111111111111111111111111101111 ,
#95000
0*
#100000
1%
b01 &
b00000000001000 '
b11111111111111110000000000000000 )
1*
b11111111111111111111111111101111 +
b11111111111111111011111011101111 ,
#105000
0*
#110000
1*
b11111111111111111011111011101111 +
